examples/play.py
examples/process.py
examples/record.py
examples/synth.py
examples/wholefile.py
wavefile/__init__.py
wavefile/libsndfile.py
wavefile/wavefile.py
wavefile/wavefile_test.py
wavefile-1.6.3.dist-info/METADATA
wavefile-1.6.3.dist-info/WHEEL
wavefile-1.6.3.dist-info/top_level.txt
wavefile-1.6.3.dist-info/RECORD
