Metadata-Version: 2.1
Name: wavefile
Version: 1.6.3
Summary: Pythonic wave file reader and writer
Author-email: David García Garzón <voki@canvoki.net>
Project-URL: Homepage, https://github.com/vokimon/python-wavefile
Project-URL: Documentation, https://readthedocs.org
Project-URL: Repository, https://github.com/vokimon/python-wavefile
Project-URL: Changelog, https://github.com/vokimon/python-wavefile/blob/master/CHANGELOG.md
Keywords: audio,wavefile,libsndfile
Classifier: Programming Language :: Python
Classifier: Programming Language :: Python :: 3
Classifier: Topic :: Multimedia
Classifier: Topic :: Scientific/Engineering
Classifier: Topic :: Software Development :: Libraries :: Python Modules
Classifier: Intended Audience :: Developers
Classifier: Intended Audience :: Science/Research
Classifier: Development Status :: 5 - Production/Stable
Classifier: License :: OSI Approved :: GNU General Public License v3 or later (GPLv3+)
Classifier: Operating System :: OS Independent
Requires-Python: >=3.8
Requires-Dist: numpy
Provides-Extra: test
Requires-Dist: pytest; extra == "test"
Requires-Dist: pytest-cov; extra == "test"
Provides-Extra: examples
Requires-Dist: PyAudio; extra == "examples"
